joymote/__init__.py
joymote/__main__.py
joymote/config.py
joymote/util.py
joymote/version.py
joymote/device/__init__.py
joymote/device/analog.py
joymote/devicemanager/__init__.py
joymote-0.0.4.dist-info/METADATA
joymote-0.0.4.dist-info/WHEEL
joymote-0.0.4.dist-info/entry_points.txt
joymote-0.0.4.dist-info/licenses/LICENSE
joymote-0.0.4.dist-info/RECORD
