Metadata-Version: 2.4
Name: joymote
Version: 0.0.4
Summary: Use Joy-Con or Pro Controller as remote control of Linux machine.
Project-URL: Homepage, https://github.com/kkoyung/joymote
Project-URL: Documentation, https://github.com/kkoyung/joymote#readme
Project-URL: Repository, https://github.com/kkoyung/joymote
Project-URL: Issue, https://github.com/kkoyung/joymote/issues
Author-email: Kingsley Yung <kingsley@kkoyung.dev>
License-File: LICENSE
Requires-Python: >=3.13
Requires-Dist: evdev>=1.9.2
Requires-Dist: pyudev>=0.24.3
